LICENSE
MANIFEST.in
README.md
setup.py
matplotlib_cn/SimHei.ttf
matplotlib_cn/__init__.py
matplotlib_cn/matplotlib_util.py
matplotlib_cn.egg-info/PKG-INFO
matplotlib_cn.egg-info/SOURCES.txt
matplotlib_cn.egg-info/dependency_links.txt
matplotlib_cn.egg-info/top_level.txt