Metadata-Version: 2.4
Name: matplotlib_cn
Version: 1.0.6
Summary: matplotlib_cn
Home-page: https://github.com/Castlebin/matplotlib-cn
Author: matplotlib_cn
Author-email: matplotlib_cn@qq.com
Classifier: Programming Language :: Python :: 3.8
Classifier: License :: OSI Approved :: Apache Software License
Classifier: Operating System :: OS Independent
License-File: LICENSE
Dynamic: author
Dynamic: author-email
Dynamic: classifier
Dynamic: description
Dynamic: description-content-type
Dynamic: home-page
Dynamic: license-file
Dynamic: summary
